LICENSE
README.md
setup.py
prompt_me/__init__.py
prompt_me/chatbot.py
prompt_me/config.py
prompt_me/conversation.py
prompt_me.egg-info/PKG-INFO
prompt_me.egg-info/SOURCES.txt
prompt_me.egg-info/dependency_links.txt
prompt_me.egg-info/top_level.txt
prompt_me/llm/__init__.py
prompt_me/llm/base.py
prompt_me/llm/chat.py
prompt_me/llm/openai.py
prompt_me/memory/__init__.py
prompt_me/preset_role/__init__.py
prompt_me/preset_role/base.py
prompt_me/preset_role/roles.py
prompt_me/tools/__init__.py
prompt_me/tools/duckduckgo.py
prompt_me/utils/__init__.py
prompt_me/utils/singleton.py
prompt_me/utils/utils.py