Metadata-Version: 2.1
Name: prompt-me
Version: 2.1.0
Summary: A lightweight LLM Prompt Layer framework
Home-page: https://github.com/Undertone0809/prompt-me
Author: Zeeland
Author-email: zeeland@foxmail.com
License: Apache 2.0
Keywords: prompt-me,prompt,chatgpt,gpt,chatbot,llm
Classifier: Development Status :: 3 - Alpha
Classifier: Intended Audience :: Developers
Classifier: Programming Language :: Python :: 3
Classifier: Programming Language :: Python :: 3.7
Classifier: Programming Language :: Python :: 3.8
Classifier: Programming Language :: Python :: 3.9
Classifier: Programming Language :: Python :: 3.10
Classifier: Programming Language :: Python :: 3.11
Classifier: Programming Language :: Python :: 3 :: Only
Classifier: License :: OSI Approved :: Apache Software License
Classifier: Operating System :: OS Independent
License-File: LICENSE
